Metadata-Version: 2.1
Name: valida_doc
Version: 0.0.1
Summary: Biblioteca para validação de documentos
Author-email: caseiro.gui@hotmail.com
License: MIT License
Keywords: validar documento cpf rg
License-File: LICENSE
